odoo/addons/mis_template_financial_report/README.rst
odoo/addons/mis_template_financial_report/__init__.py
odoo/addons/mis_template_financial_report/__manifest__.py
odoo/addons/mis_template_financial_report/data/mis_report.xml
odoo/addons/mis_template_financial_report/data/mis_report_kpi.xml
odoo/addons/mis_template_financial_report/data/mis_report_style.xml
odoo/addons/mis_template_financial_report/data/mis_report_subreport.xml
odoo/addons/mis_template_financial_report/i18n/es.po
odoo/addons/mis_template_financial_report/i18n/fi.po
odoo/addons/mis_template_financial_report/i18n/fr.po
odoo/addons/mis_template_financial_report/i18n/mis_template_financial_report.pot
odoo/addons/mis_template_financial_report/models/__init__.py
odoo/addons/mis_template_financial_report/models/mis_report_instance.py
odoo/addons/mis_template_financial_report/readme/CONFIGURE.rst
odoo/addons/mis_template_financial_report/readme/CONTRIBUTORS.rst
odoo/addons/mis_template_financial_report/readme/DESCRIPTION.rst
odoo/addons/mis_template_financial_report/readme/ROADMAP.rst
odoo/addons/mis_template_financial_report/readme/USAGE.rst
odoo/addons/mis_template_financial_report/readme/newsfragments/.gitkeep
odoo/addons/mis_template_financial_report/static/description/icon.png
odoo/addons/mis_template_financial_report/static/description/index.html
odoo/addons/mis_template_financial_report/static/src/css/mis_template_financial_report.css
odoo/addons/mis_template_financial_report/static/src/css/report.css
odoo/addons/mis_template_financial_report/static/src/xml/mis_template_financial_report.xml
odoo/addons/mis_template_financial_report/tests/__init__.py
odoo/addons/mis_template_financial_report/tests/test_mis_template_financial_report.py
odoo/addons/mis_template_financial_report/views/mis_report_instance_views.xml
odoo/addons/mis_template_financial_report/views/templates.xml
odoo14_addon_mis_template_financial_report-14.0.1.1.1.dist-info/METADATA
odoo14_addon_mis_template_financial_report-14.0.1.1.1.dist-info/WHEEL
odoo14_addon_mis_template_financial_report-14.0.1.1.1.dist-info/top_level.txt
odoo14_addon_mis_template_financial_report-14.0.1.1.1.dist-info/RECORD
